pymod/__about__.py
pymod/__init__.py
pymod/__main__.py
pymod/pymod.py
pymod_amiga-1.1.2.dist-info/METADATA
pymod_amiga-1.1.2.dist-info/WHEEL
pymod_amiga-1.1.2.dist-info/entry_points.txt
pymod_amiga-1.1.2.dist-info/licenses/LICENSE
pymod_amiga-1.1.2.dist-info/RECORD
