Metadata-Version: 2.3
Name: pymod-amiga
Version: 1.1.2
Summary: Python program that plays/renders ProTracker modules using PyAudio.
Project-URL: Homepage, https://verycheapwebsite.rf.gd/pymod
Project-URL: Source Code, https://github.com/Prezzodaman/pymod
Project-URL: Bug Tracker, https://github.com/Prezzodaman/pymod/issues
Author-email: Presley Peters <presleypeters04@gmail.com>
License-Expression: GPL-3.0-or-later
License-File: LICENSE
Keywords: amiga,protracker,soundtracker
Classifier: Development Status :: 4 - Beta
Classifier: Programming Language :: Python
Classifier: Programming Language :: Python :: Implementation :: CPython
Classifier: Programming Language :: Python :: Implementation :: PyPy
Requires-Python: >=3.8
Requires-Dist: pyaudio
